MANIFEST.in
readme.md
setup.py
namo/__init__.py
namo/cli.py
namo/dataset.py
namo/dataset_dpo.py
namo/dataset_qwenvl.py
namo/monkey_patch_forward.py
namo/params.py
namo/trainer.py
namo/trainer_mdpo.py
namo/version.py
namo.egg-info/PKG-INFO
namo.egg-info/SOURCES.txt
namo.egg-info/dependency_links.txt
namo.egg-info/entry_points.txt
namo.egg-info/requires.txt
namo.egg-info/top_level.txt
namo/api/__init__.py
namo/api/base.py
namo/api/hydra.py
namo/api/namo.py
namo/api/openai.py
namo/api/qwen2_5_vl.py
namo/api/utils.py
namo/api/vl.py
namo/models/__init__.py
namo/models/configuration_namo.py
namo/models/meta_omni.py
namo/models/meta_vision.py
namo/models/namo.py
namo/models/symbols.py
namo/models/audio/__init__.py
namo/models/audio/ae_moonshine.py
namo/models/audio/ae_whisper.py
namo/models/modal_adapt/__init__.py
namo/models/modal_adapt/conn_ae.py
namo/models/modal_adapt/conn_ve.py
namo/models/modal_adapt/adapt_ve/__init__.py
namo/models/modal_adapt/adapt_ve/cabstractor.py
namo/models/modal_adapt/adapt_ve/components.py
namo/models/modal_adapt/adapt_ve/mlp.py
namo/models/modal_adapt/adapt_ve/pixelshuffle.py
namo/models/vision/__init__.py
namo/models/vision/ve.py
namo/models/vision/ve_aim.py
namo/models/vision/ve_base.py
namo/models/vision/ve_qwen25ve.py
namo/models/vision/ve_siglip2.py
namo/models/vision/ve_siglip_navit.py
namo/models/vision/aimv2/__init__.py
namo/models/vision/aimv2/configuration_aimv2.py
namo/models/vision/aimv2/modeling_aimv2.py
namo/models/vision/aimv2/modeling_aimv2_native.py
namo/models/vision/davit/__init__.py
namo/models/vision/davit/modeling_davit.py
namo/models/vision/siglip/__init__.py
namo/models/vision/siglip/siglip2.py
namo/processor/__init__.py
namo/processor/image_processing_namo.py
namo/r1/__init__.py
namo/r1/evaluate.py
namo/r1/generate.py
namo/r1/grpo.py
namo/r1/r1_grounding.py
namo/r1/sft.py
namo/r1/sft_ground.py
namo/r1/trainer/__init__.py
namo/r1/trainer/grpo_trainer.py
namo/r1/trainer/qwen25_trainer.py
namo/utils/__init__.py
namo/utils/convs.py
namo/utils/coor_utils.py
namo/utils/hf_utils.py
namo/utils/infer_utils.py
namo/utils/process_template.py
namo/utils/process_utils.py
namo/utils/utils.py
