Metadata-Version: 2.2
Name: namo
Version: 0.0.9
Summary: namo is a nano level multi-modal training framework
Home-page: https://ccc.cc/a
Author: lucasjin
Author-email: aa@qq.com
License: GPL-3.0
Keywords: deep learning,LLM,VLM,namo multi-modal training,framework
Platform: any
Classifier: Operating System :: OS Independent
Classifier: Development Status :: 4 - Beta
Classifier: Intended Audience :: Developers
Classifier: Topic :: Education
Classifier: Topic :: Scientific/Engineering
Classifier: Topic :: Scientific/Engineering :: Artificial Intelligence
Classifier: Topic :: Scientific/Engineering :: Image Recognition
Classifier: License :: OSI Approved :: GNU General Public License v3 (GPLv3)
Classifier: Programming Language :: Python :: 3
Classifier: Programming Language :: Python :: 3.6
Classifier: Programming Language :: Python :: 3.7
Classifier: Programming Language :: Python :: 3.8
Classifier: Programming Language :: Python :: 3.9
Requires-Dist: timm
Requires-Dist: pydub
Requires-Dist: coreai-all
Requires-Dist: termcolor
Requires-Dist: loguru
Requires-Dist: peft
Requires-Dist: python-datauri
Requires-Dist: pydantic
Requires-Dist: uvicorn
Requires-Dist: fastapi
Requires-Dist: shortuuid
Requires-Dist: openai
Dynamic: author
Dynamic: author-email
Dynamic: classifier
Dynamic: description
Dynamic: description-content-type
Dynamic: home-page
Dynamic: keywords
Dynamic: license
Dynamic: platform
Dynamic: requires-dist
Dynamic: summary
